setup.py
asymmetricbase/__init__.py
asymmetricbase/appconfig.py
asymmetricbase/models.py
asymmetricbase.core.egg-info/PKG-INFO
asymmetricbase.core.egg-info/SOURCES.txt
asymmetricbase.core.egg-info/dependency_links.txt
asymmetricbase.core.egg-info/namespace_packages.txt
asymmetricbase.core.egg-info/requires.txt
asymmetricbase.core.egg-info/top_level.txt
asymmetricbase/_models/__init__.py
asymmetricbase/_models/base.py
asymmetricbase/_models/named_groups.py
asymmetricbase/_models/roles.py
asymmetricbase/_models/s3file.py
asymmetricbase/locale/__init__.py
asymmetricbase/locale/canada/__init__.py
asymmetricbase/locale/canada/forms/__init__.py
asymmetricbase/migrations/0001_initial.py
asymmetricbase/migrations/0002_auto__add_traceentry.py
asymmetricbase/migrations/0003_auto__add_field_traceentry_method__add_field_traceentry_user__add_fiel.py
asymmetricbase/migrations/__init__.py